stock_mcp_server/__init__.py
stock_mcp_server/config.py
stock_mcp_server/py.typed
stock_mcp_server/server.py
stock_mcp_server/models/__init__.py
stock_mcp_server/models/indicators.py
stock_mcp_server/models/market.py
stock_mcp_server/models/news.py
stock_mcp_server/models/sentiment.py
stock_mcp_server/resources/__init__.py
stock_mcp_server/resources/market_resources.py
stock_mcp_server/services/__init__.py
stock_mcp_server/services/akshare_service.py
stock_mcp_server/services/cache_service.py
stock_mcp_server/services/data_source_manager.py
stock_mcp_server/services/indicator_service.py
stock_mcp_server/services/news_service.py
stock_mcp_server/services/sentiment_service.py
stock_mcp_server/tools/__init__.py
stock_mcp_server/tools/advice.py
stock_mcp_server/tools/indicators.py
stock_mcp_server/tools/macro.py
stock_mcp_server/tools/market_data.py
stock_mcp_server/tools/money_flow.py
stock_mcp_server/tools/news.py
stock_mcp_server/tools/overview.py
stock_mcp_server/tools/sector.py
stock_mcp_server/tools/sentiment.py
stock_mcp_server/tools/special.py
stock_mcp_server/utils/__init__.py
stock_mcp_server/utils/date_utils.py
stock_mcp_server/utils/json_utils.py
stock_mcp_server/utils/logger.py
stock_mcp_server/utils/validators.py
stock_mcp_server-0.1.2.dist-info/METADATA
stock_mcp_server-0.1.2.dist-info/WHEEL
stock_mcp_server-0.1.2.dist-info/entry_points.txt
stock_mcp_server-0.1.2.dist-info/licenses/LICENSE
stock_mcp_server-0.1.2.dist-info/RECORD
