Metadata-Version: 2.4
Name: stock-mcp-server
Version: 0.1.2
Summary: MCP server providing comprehensive Chinese A-share stock market data and analysis
Project-URL: Homepage, https://github.com/yourusername/stock-mcp-server
Project-URL: Repository, https://github.com/yourusername/stock-mcp-server
Project-URL: Documentation, https://github.com/yourusername/stock-mcp-server#readme
Author-email: Your Name <your.email@example.com>
License: MIT
License-File: LICENSE
Keywords: a-share,finance,market-data,mcp,stock,technical-analysis
Classifier: Development Status :: 3 - Alpha
Classifier: Intended Audience :: Developers
Classifier: License :: OSI Approved :: MIT License
Classifier: Programming Language :: Python :: 3
Classifier: Programming Language :: Python :: 3.10
Classifier: Programming Language :: Python :: 3.11
Classifier: Programming Language :: Python :: 3.12
Requires-Python: >=3.12
Requires-Dist: aiohttp>=3.9.0
Requires-Dist: akshare>=1.14.0
Requires-Dist: beautifulsoup4>=4.12.0
Requires-Dist: cachetools>=5.3.0
Requires-Dist: jieba>=0.42.1
Requires-Dist: loguru>=0.7.0
Requires-Dist: lxml>=4.9.0
Requires-Dist: mcp>=0.9.0
Requires-Dist: pandas-ta>=0.3.14b0
Requires-Dist: pandas>=2.0.0
Requires-Dist: pydantic>=2.0.0
Requires-Dist: pyyaml>=6.0
Requires-Dist: requests>=2.31.0
Requires-Dist: snownlp>=0.12.3
Requires-Dist: sqlalchemy>=2.0.0
Provides-Extra: dev
Requires-Dist: black>=23.0.0; extra == 'dev'
Requires-Dist: mypy>=1.5.0; extra == 'dev'
Requires-Dist: pytest-asyncio>=0.21.0; extra == 'dev'
Requires-Dist: pytest-cov>=4.1.0; extra == 'dev'
Requires-Dist: pytest>=7.4.0; extra == 'dev'
Requires-Dist: ruff>=0.1.0; extra == 'dev'
Requires-Dist: types-beautifulsoup4>=4.12.0; extra == 'dev'
Requires-Dist: types-cachetools>=5.3.0; extra == 'dev'
Requires-Dist: types-pyyaml>=6.0.0; extra == 'dev'
Requires-Dist: types-requests>=2.31.0; extra == 'dev'
